{"errors":[],"warnings":["./src/components/footer.js\nModule Warning (from ./node_modules/eslint-loader/index.js):\n\u001b[0m\u001b[0m\n\u001b[0m\u001b[4m/home/tricore19/Desktop/my-first-gatsby-site/src/components/footer.js\u001b[24m\u001b[0m\n\u001b[0m  \u001b[2m3:9\u001b[22m   \u001b[33mwarning\u001b[39m  'useStaticQuery' is defined but never used  \u001b[2mno-unused-vars\u001b[22m\u001b[0m\n\u001b[0m  \u001b[2m3:25\u001b[22m  \u001b[33mwarning\u001b[39m  'graphql' is defined but never used         \u001b[2mno-unused-vars\u001b[22m\u001b[0m\n\u001b[0m  \u001b[2m4:9\u001b[22m   \u001b[33mwarning\u001b[39m  'Navbar' is defined but never used          \u001b[2mno-unused-vars\u001b[22m\u001b[0m\n\u001b[0m  \u001b[2m4:16\u001b[22m  \u001b[33mwarning\u001b[39m  'Nav' is defined but never used             \u001b[2mno-unused-vars\u001b[22m\u001b[0m\n\u001b[0m  \u001b[2m4:20\u001b[22m  \u001b[33mwarning\u001b[39m  'Form' is defined but never used            \u001b[2mno-unused-vars\u001b[22m\u001b[0m\n\u001b[0m  \u001b[2m4:25\u001b[22m  \u001b[33mwarning\u001b[39m  'FormControl' is defined but never used     \u001b[2mno-unused-vars\u001b[22m\u001b[0m\n\u001b[0m  \u001b[2m4:37\u001b[22m  \u001b[33mwarning\u001b[39m  'Button' is defined but never used          \u001b[2mno-unused-vars\u001b[22m\u001b[0m\n\u001b[0m\u001b[0m\n\u001b[0m\u001b[33m\u001b[1m✖ 7 problems (0 errors, 7 warnings)\u001b[22m\u001b[39m\u001b[0m\n\u001b[0m\u001b[33m\u001b[1m\u001b[22m\u001b[39m\u001b[0m","./src/components/layout.js\nModule Warning (from ./node_modules/eslint-loader/index.js):\n\u001b[0m\u001b[0m\n\u001b[0m\u001b[4m/home/tricore19/Desktop/my-first-gatsby-site/src/components/layout.js\u001b[24m\u001b[0m\n\u001b[0m  \u001b[2m3:20\u001b[22m  \u001b[33mwarning\u001b[39m  'Form' is defined but never used           \u001b[2mno-unused-vars\u001b[22m\u001b[0m\n\u001b[0m  \u001b[2m3:25\u001b[22m  \u001b[33mwarning\u001b[39m  'FormControl' is defined but never used    \u001b[2mno-unused-vars\u001b[22m\u001b[0m\n\u001b[0m  \u001b[2m3:37\u001b[22m  \u001b[33mwarning\u001b[39m  'Button' is defined but never used         \u001b[2mno-unused-vars\u001b[22m\u001b[0m\n\u001b[0m  \u001b[2m6:9\u001b[22m   \u001b[33mwarning\u001b[39m  'data' is assigned a value but never used  \u001b[2mno-unused-vars\u001b[22m\u001b[0m\n\u001b[0m\u001b[0m\n\u001b[0m\u001b[33m\u001b[1m✖ 4 problems (0 errors, 4 warnings)\u001b[22m\u001b[39m\u001b[0m\n\u001b[0m\u001b[33m\u001b[1m\u001b[22m\u001b[39m\u001b[0m","./src/pages/about.js\nModule Warning (from ./node_modules/eslint-loader/index.js):\n\u001b[0m\u001b[0m\n\u001b[0m\u001b[4m/home/tricore19/Desktop/my-first-gatsby-site/src/pages/about.js\u001b[24m\u001b[0m\n\u001b[0m  \u001b[2m6:8\u001b[22m  \u001b[33mwarning\u001b[39m  'Blank' is defined but never used  \u001b[2mno-unused-vars\u001b[22m\u001b[0m\n\u001b[0m\u001b[0m\n\u001b[0m\u001b[33m\u001b[1m✖ 1 problem (0 errors, 1 warning)\u001b[22m\u001b[39m\u001b[0m\n\u001b[0m\u001b[33m\u001b[1m\u001b[22m\u001b[39m\u001b[0m","./src/pages/index.js\nModule Warning (from ./node_modules/eslint-loader/index.js):\n\u001b[0m\u001b[0m\n\u001b[0m\u001b[4m/home/tricore19/Desktop/my-first-gatsby-site/src/pages/index.js\u001b[24m\u001b[0m\n\u001b[0m  \u001b[2m5:8\u001b[22m  \u001b[33mwarning\u001b[39m  'Blank' is defined but never used                                                                                                                                                                                                                                       \u001b[2mno-unused-vars\u001b[22m\u001b[0m\n\u001b[0m  \u001b[2m9:1\u001b[22m  \u001b[33mwarning\u001b[39m  Anonymous arrow functions cause Fast Refresh to not preserve local component state.\u001b[0m\n\u001b[0m\u001b[0m\n\u001b[0m       Please add a name to your function, for example:\u001b[0m\n\u001b[0m\u001b[0m\n\u001b[0m       Before:\u001b[0m\n\u001b[0m       export default () => {}\u001b[0m\n\u001b[0m\u001b[0m\n\u001b[0m       After:\u001b[0m\n\u001b[0m       const Named = () => {}\u001b[0m\n\u001b[0m       export default Named;\u001b[0m\n\u001b[0m  \u001b[2mno-anonymous-exports-page-templates\u001b[22m\u001b[0m\n\u001b[0m\u001b[0m\n\u001b[0m\u001b[33m\u001b[1m✖ 2 problems (0 errors, 2 warnings)\u001b[22m\u001b[39m\u001b[0m\n\u001b[0m\u001b[33m\u001b[1m\u001b[22m\u001b[39m\u001b[0m"],"namedChunkGroups":{"polyfill":{"chunks":["polyfill"],"assets":["polyfill.js"],"children":{},"childAssets":{}},"commons":{"chunks":["commons"],"assets":["commons.css","commons.js","commons.b7b3cf3f9132718bd8a9.hot-update.js"],"children":{},"childAssets":{}}},"assetsByChunkName":{"polyfill":["polyfill.js"],"commons":["commons.css","commons.js","commons.b7b3cf3f9132718bd8a9.hot-update.js"]}}